wordiff/__init__.py
wordiff/wordiff.py
wordiff-0.0.1.dist-info/METADATA
wordiff-0.0.1.dist-info/WHEEL
wordiff-0.0.1.dist-info/licenses/LICENSE
wordiff-0.0.1.dist-info/RECORD
