Metadata-Version: 2.1
Name: wordiff
Version: 0.0.1
Summary: Identify the most distinctive words when comparing text across different groups.
Project-URL: Homepage, https://github.com/abitmarty/wordiff
Author-email: Abitmarty <author@example.com>
License-File: LICENSE
Classifier: License :: OSI Approved :: MIT License
Classifier: Operating System :: OS Independent
Classifier: Programming Language :: Python :: 3
Requires-Python: >=3.7
